Metadata-Version: 2.4
Name: llama-index-embeddings-databricks
Version: 0.4.1
Summary: llama-index embeddings databricks integration
Author: Enrico Stauss
License-Expression: MIT
License-File: LICENSE
Requires-Python: <4.0,>=3.9
Requires-Dist: llama-index-core<0.15,>=0.13.0
Requires-Dist: llama-index-embeddings-openai<0.6,>=0.5.0
